{"nuwZmEmOgUEDU5RlSiPgQw==":"ivan%20difuminado-529x517.png","XWjRGwgqwcGcYd9VNPCXGA==":"tutto%20fondo%20blanco-529x517.png","fZrttnaN083zmFI8w9PGWQ==":"tutto%20fondo%20blanco-528x516.png","s6qPaHmiX5oWe4bpqxlenQ==":"tutto%20fondo%20reflejo-529x517.png","8f22Z9SPMhP6rKoSX90s0g==":"anabel-576x747.jpg","fWK+ZF8vS5bkBiVfgPctvw==":"img_20181021-162556-576x1026.jpg","hqu5UKoC9EN4lFclioFb9A==":"anabel-crop-576x821.jpg","X1cp4RMzxiLyGH0xf/CY9g==":"sabore%20caf%C3%A9-crop-576x586.jpg","89lrUFqHhjOPPZa6gqNfLA==":"anabel%20perfilado-309x400.jpg","JEgmnw9Bq7mG9aupvhrAAA==":"sabore%20caf%C3%A9-crop2-393x400.jpg","LGiulRhITq1o6lYN3/RtOA==":"certificado-web-150x150.jpg","pI6f2ktV7nzecf0uJ3zv4g==":"consultor%20people%20keys-305x186.png"}